{
  "logo_suite": [
    "Primary lockup: Route lines or branching node flow mark. with the full business name.",
    "Icon mark: simplify the Route lines or branching node flow mark. into a square avatar for favicons, socials, and app badges.",
    "Text-only wordmark: keep one clean horizontal version for signatures, invoices, PDFs, and letterhead."
  ],
  "support_inboxes": {
    "primary": "support@theleadflowhq.com",
    "sales": "hello@theleadflowhq.com",
    "ops": "ops@theleadflowhq.com"
  },
  "email_signature": {
    "display_name": "LeadFlow AI",
    "title_line": "Operational, urgent, and exact.",
    "website": "https://theleadflowhq.com",
    "primary_contact": "support@theleadflowhq.com",
    "accent": "#10B981"
  },
  "letterhead": [
    "Top band uses the primary color, logo lockup, and one short positioning line.",
    "Contact block shows website, support inbox, and one escalation inbox in the footer.",
    "Invoices, proposals, and one-page PDFs keep the display font for headings and the body font for all operational copy."
  ],
  "social_profiles": [
    {
      "platform": "Instagram",
      "handle": "@theleadflowhq",
      "bio_focus": "Audit pages, routing demos, and pilot screens all need one crisp diagnostic visual system tied to actual routing logic"
    },
    {
      "platform": "Facebook",
      "handle": "@theleadflowhq",
      "bio_focus": "Audit pages, routing demos, and pilot screens all need one crisp diagnostic visual system tied to actual routing logic"
    },
    {
      "platform": "TikTok",
      "handle": "@theleadflowhq",
      "bio_focus": "Audit pages, routing demos, and pilot screens all need one crisp diagnostic visual system tied to actual routing logic"
    },
    {
      "platform": "YouTube",
      "handle": "@theleadflowhq",
      "bio_focus": "Audit pages, routing demos, and pilot screens all need one crisp diagnostic visual system tied to actual routing logic"
    },
    {
      "platform": "X",
      "handle": "@theleadflowhq",
      "bio_focus": "Audit pages, routing demos, and pilot screens all need one crisp diagnostic visual system tied to actual routing logic"
    },
    {
      "platform": "Threads",
      "handle": "@theleadflowhq",
      "bio_focus": "Audit pages, routing demos, and pilot screens all need one crisp diagnostic visual system tied to actual routing logic"
    },
    {
      "platform": "Pinterest",
      "handle": "@theleadflowhq",
      "bio_focus": "Audit pages, routing demos, and pilot screens all need one crisp diagnostic visual system tied to actual routing logic"
    },
    {
      "platform": "Snapchat",
      "handle": "@theleadflowhq",
      "bio_focus": "Audit pages, routing demos, and pilot screens all need one crisp diagnostic visual system tied to actual routing logic"
    },
    {
      "platform": "Kick",
      "handle": "@theleadflowhq",
      "bio_focus": "Audit pages, routing demos, and pilot screens all need one crisp diagnostic visual system tied to actual routing logic"
    },
    {
      "platform": "OnlyFans",
      "handle": "@theleadflowhq",
      "bio_focus": "Audit pages, routing demos, and pilot screens all need one crisp diagnostic visual system tied to actual routing logic"
    },
    {
      "platform": "LinkedIn",
      "handle": "@theleadflowhq",
      "bio_focus": "Audit pages, routing demos, and pilot screens all need one crisp diagnostic visual system tied to actual routing logic"
    }
  ],
  "posting_cadence": {
    "label": "Authority-service cadence",
    "schedule": [
      "Prepare 1 authority post each weekday, 2 short-form proof clips per week, and 1 email follow-up per week for review.",
      "Tie every post to one bounded offer, one proof point, or one objection-handling angle.",
      "Keep publication blocked until operator approval, but keep the queue continuously review-ready."
    ],
    "calendar": [
      "Monday: problem statement and stakes",
      "Tuesday: proof or diagnostic insight",
      "Wednesday: process or walkthrough",
      "Thursday: objection handling",
      "Friday: CTA and scope reminder",
      "Weekend: FAQ, recap, or evergreen library update"
    ]
  },
  "merch_review_scope": [
    "Merch is not a primary launch surface for LeadFlow AI.",
    "If created at all, keep it review-only and limited to leave-behind collateral, presentation decks, or operator onboarding materials."
  ]
}
